ezblockvirtual/__init__.py
ezblockvirtual/modules.py
ezblockvirtual-0.1.5.dist-info/METADATA
ezblockvirtual-0.1.5.dist-info/WHEEL
ezblockvirtual-0.1.5.dist-info/top_level.txt
ezblockvirtual-0.1.5.dist-info/RECORD
