Metadata-Version: 2.1
Name: ezblockvirtual
Version: 0.1.5
Summary: Sunfounder utility block to use virtual components
Home-page: https://github.com/gpspelle/ezblock-virtual-modules/
Author: gpspelle
Author-email: gpsunicamp016@gmail.com
License: MIT
Keywords: Raspberrypi,Sunfounder,Ezblock
Platform: UNKNOWN
